sturdystats/__init__.py
sturdystats/index.py
sturdystats/job.py
sturdystats/model.py
sturdy_stats_sdk-1.0.49.dist-info/METADATA
sturdy_stats_sdk-1.0.49.dist-info/WHEEL
sturdy_stats_sdk-1.0.49.dist-info/top_level.txt
sturdy_stats_sdk-1.0.49.dist-info/RECORD
