Metadata-Version: 2.4
Name: sturdy-stats-sdk
Version: 1.0.49
Summary: SDK for the Sturdy Statistics API
Home-page: https://sturdystatistics.com
Author: Kian Ghodoussi
Author-email: ghodoussikian@gmail.com
Classifier: Programming Language :: Python :: 3
Requires-Python: >=3.9
Requires-Dist: more-itertools
Requires-Dist: srsly
Requires-Dist: tenacity
Requires-Dist: pandas
Requires-Dist: numpy
Requires-Dist: requests
Provides-Extra: regression
Requires-Dist: arviz; extra == "regression"
Requires-Dist: xarray; extra == "regression"
Requires-Dist: scipy; extra == "regression"
Provides-Extra: all
Requires-Dist: arviz; extra == "all"
Requires-Dist: xarray; extra == "all"
Requires-Dist: scipy; extra == "all"
Dynamic: author
Dynamic: author-email
Dynamic: classifier
Dynamic: description
Dynamic: description-content-type
Dynamic: home-page
Dynamic: provides-extra
Dynamic: requires-dist
Dynamic: requires-python
Dynamic: summary
